LICENSE
logbookgenerator/__init__.py
logbookgenerator/computation/__init__.py
logbookgenerator/computation/code_processing.py
logbookgenerator/computation/comment_extraction.py
logbookgenerator/computation/config_generation.py
logbookgenerator/computation/context_generation.py
logbookgenerator/computation/parsing.py
logbookgenerator/computation/render_context.py
logbookgenerator/config/__init__.py
logbookgenerator/config/constants.py
logbookgenerator/config/paths.py
logbookgenerator/integrations/__init__.py
logbookgenerator/interface/__init__.py
logbookgenerator/interface/command_line.py
logbookgenerator/logs/__init__.py
logbookgenerator/logs/setup_logging.py
logbookgenerator/main.py
logbookgenerator/py.typed
logbookgenerator/templates/contents.md.j2
logbookgenerator/templates/coursework.md.j2
logbookgenerator/templates/cover.md.j2
logbookgenerator/templates/references.md.j2
logbookgenerator/templates/reflection.md.j2
logbookgenerator/templates/week.md.j2
logbookgenerator/utilities/__init__.py
logbookgenerator/utilities/file_handling.py
logbookgenerator/utilities/validation.py
logbookgenerator-1.0.15.dist-info/LICENSE
logbookgenerator-1.0.15.dist-info/METADATA
logbookgenerator-1.0.15.dist-info/WHEEL
logbookgenerator-1.0.15.dist-info/entry_points.txt
logbookgenerator-1.0.15.dist-info/RECORD
