Metadata-Version: 2.1
Name: logbookgenerator
Version: 1.0.15
Summary: Generates a logbook. Designed for the University of Lincoln's Scientific Computing module.
Home-page: https://github.com/unkokaeru/logbookgenerator
License: MIT
Author: William Fayers
Author-email: william@fayers.com
Requires-Python: >=3.10,<4.0
Classifier: License :: OSI Approved :: MIT License
Classifier: Programming Language :: Python :: 3
Classifier: Programming Language :: Python :: 3.10
Classifier: Programming Language :: Python :: 3.11
Classifier: Programming Language :: Python :: 3.12
Classifier: Programming Language :: Python :: 3.13
Requires-Dist: jinja2 (>=3.1.4,<4.0.0)
Requires-Dist: pyyaml (>=6.0.2,<7.0.0)
Requires-Dist: questionary (>=2.0.1,<3.0.0)
Requires-Dist: rich (>=13.7.1,<14.0.0)
Project-URL: Repository, https://github.com/unkokaeru/logbookgenerator
